beak/__init__.py
beak/beak.py
beak-0.0.1b0.dist-info/LICENSE
beak-0.0.1b0.dist-info/METADATA
beak-0.0.1b0.dist-info/WHEEL
beak-0.0.1b0.dist-info/top_level.txt
beak-0.0.1b0.dist-info/RECORD
